mangadex/__init__.py
mangadex/auth.py
mangadex/errors.py
mangadex/people.py
mangadex/series.py
mangadex/url_models.py
mangadex-2.7.dist-info/LICENSE
mangadex-2.7.dist-info/METADATA
mangadex-2.7.dist-info/WHEEL
mangadex-2.7.dist-info/top_level.txt
mangadex-2.7.dist-info/RECORD
