Metadata-Version: 2.1
Name: mangadex
Version: 2.7
Summary: Python wrapper for the mangadex API
Download-URL: https://github.com/EMACC99/mangadex/releases
Author: Eduardo Ceja
License: MIT
Keywords: python,mangadex
Requires-Python: >=3.6
License-File: LICENSE
Requires-Dist: requests
Requires-Dist: future
Requires-Dist: python-dateutil
Requires-Dist: pytest
Requires-Dist: typing-extensions
